offsetbasedgraph/GRCH38.py
offsetbasedgraph/__init__.py
offsetbasedgraph/cigar_align.py
offsetbasedgraph/config.py
offsetbasedgraph/gene.py
offsetbasedgraph/genematcher.py
offsetbasedgraph/graph.py
offsetbasedgraph/graphcreators.py
offsetbasedgraph/graphinterval.py
offsetbasedgraph/graphutils.py
offsetbasedgraph/interval.py
offsetbasedgraph/multipathinterval.py
offsetbasedgraph/regionpath.py
offsetbasedgraph/sequences.py
offsetbasedgraph/translation.py
offsetbasedgraph/util.py
offsetbasedgraph-1.0.2.dist-info/DESCRIPTION.rst
offsetbasedgraph-1.0.2.dist-info/METADATA
offsetbasedgraph-1.0.2.dist-info/RECORD
offsetbasedgraph-1.0.2.dist-info/WHEEL
offsetbasedgraph-1.0.2.dist-info/metadata.json
offsetbasedgraph-1.0.2.dist-info/top_level.txt
