Metadata-Version: 2.0
Name: offsetbasedgraph
Version: 1.0.2
Summary: Offset based graph
Home-page: http://github.com/uio-cels/offsetbasedgraph
Author: Ivar Grytten and Knut Rand
Author-email: UNKNOWN
License: MIT
Platform: UNKNOWN
Requires-Dist: future
Requires-Dist: numpy
Requires-Dist: pymysql
